commands/__init__.py
commands/install.py
commands/list.py
commands/uninstall.py
commands/use.py
commons/__init__.py
commons/config.py
terraenv-0.12.data/scripts/terraenv
terraenv-0.12.dist-info/LICENSE
terraenv-0.12.dist-info/METADATA
terraenv-0.12.dist-info/WHEEL
terraenv-0.12.dist-info/top_level.txt
terraenv-0.12.dist-info/RECORD
