Metadata-Version: 2.1
Name: terraenv
Version: 0.12
Summary: Terraform and Terragrunt Version Manager
Home-page: https://github.com/aaratn/terraenv
Author: Aarat Nathwani
Author-email: me@aarat.com
License: MIT
Platform: UNKNOWN
Classifier: Programming Language :: Python :: 3
Classifier: License :: OSI Approved :: MIT License
Classifier: Operating System :: OS Independent
Requires-Python: >=3.6
Requires-Dist: altgraph (==0.16.1)
Requires-Dist: appdirs (==1.4.3)
Requires-Dist: beautifulsoup4 (==4.8.1)
Requires-Dist: bs4 (==0.0.1)
Requires-Dist: certifi (==2019.9.11)
Requires-Dist: chardet (==3.0.4)
Requires-Dist: cssselect (==1.1.0)
Requires-Dist: fake-useragent (==0.1.11)
Requires-Dist: idna (==2.8)
Requires-Dist: lxml (==4.6.2)
Requires-Dist: macholib (==1.11)
Requires-Dist: parse (==1.12.1)
Requires-Dist: pyee (==6.0.0)
Requires-Dist: pyppeteer (==0.0.25)
Requires-Dist: pyquery (==1.4.1)
Requires-Dist: python-dotenv (==0.10.3)
Requires-Dist: requests (==2.22.0)
Requires-Dist: requests-html (==0.10.0)
Requires-Dist: six (==1.13.0)
Requires-Dist: soupsieve (==1.9.5)
Requires-Dist: tqdm (==4.38.0)
Requires-Dist: urllib3 (==1.25.7)
Requires-Dist: w3lib (==1.21.0)
Requires-Dist: websockets (==8.1)
